cmsplugin_flickr_player
