Metadata-Version: 1.1
Name: cmsplugin-flickr-player
Version: 0.2.9.8
Summary: Flickr iframe with photo set for django-cms
Home-page: https://github.com/elcodo/cmsplugin-flickr-player
Author: ELCODO
Author-email: info@elcodo.pl
License: The MIT License (MIT)
